{
  "kind": "collectionType",
  "collectionName": "accounts",
  "info": {
    "singularName": "account",
    "pluralName": "accounts",
    "displayName": "Account",
    "description": ""
  },
  "options": {
    "draftAndPublish": false
  },
  "pluginOptions": {},
  "attributes": {
    "name": {
      "type": "string"
    },
    "type": {
      "type": "string"
    },
    "status": {
      "type": "string"
    },
    "Marketingpreferences": {
      "type": "component",
      "repeatable": true,
      "component": "marketingpreferences.marketingpreferences"
    },
    "users": {
      "type": "relation",
      "relation": "oneToMany",
      "target": "plugin::users-permissions.user",
      "mappedBy": "account"
    }
  }
}
